{
  "id": "ms-en-ro-definitive",
  "parent": "ms-ro-definitiv-869df85a@eb8404d84f439947f7ccbbf903c4bfd5",
  "part_of_speech": "adjective",
  "tags": [
    "level:b1",
    "etymology:latin",
    "topic:concepts-abstract",
    "register:neutral",
    "property:quality"
  ],
  "sourceLanguage": "en",
  "targetLanguage": "ro",
  "metadata": {
    "author": "mschwehl",
    "source": "swipedict-en-ro",
    "contentVersion": 1,
    "schemaVersion": "1.0"
  },
  "source": {
    "lang": "en",
    "headword": "definitive",
    "definition": "Irrevocable, final, and conclusively established.",
    "pronunciation": "/dɪˈfɪnɪtɪv/",
    "etymology": {
      "explanation": {
        "sourceText": "The English adjective 'definitive' comes from the Latin 'definitivus', meaning 'settled' or 'determined'.",
        "targetText": "Adjectivul englezesc „definitive” provine din latină 'definitivus', care înseamnă 'finalizat' sau 'precizat'."
      },
      "source": "Etymological Dictionaries, Linguistic Analysis"
    }
  },
  "target": {
    "lang": "ro",
    "headword": "definitiv",
    "definition": "Care este irevocabil, final și stabilit definitiv.",
    "pronunciation": "/definiˈtiv/",
    "etymology": {
      "explanation": {
        "sourceText": "The Romanian word 'definitiv' comes from the Latin 'definitivus', meaning 'completed' or 'specified'.",
        "targetText": "Cuvântul românesc „definitiv” provine din latină 'definitivus', care înseamnă 'finalizat' sau 'precizat'."
      },
      "source": "Etymological Dictionaries, Linguistic Analysis"
    }
  },
  "senses": [],
  "relatedWords": [
    {
      "sourceText": "final",
      "targetText": "final"
    },
    {
      "sourceText": "end",
      "targetText": "sfârșit"
    },
    {
      "sourceText": "valid",
      "targetText": "valabil"
    },
    {
      "sourceText": "irrevocable",
      "targetText": "irevocabil"
    }
  ],
  "antonyms": [
    {
      "sourceText": "provisional",
      "targetText": "provizoriu"
    }
  ],
  "examples": [
    {
      "sourceText": "The decision is definitive.",
      "targetText": "Decizia este definitivă."
    },
    {
      "sourceText": "The result is definitive and cannot be changed.",
      "targetText": "Rezultatul este definitiv și nu poate fi schimbat."
    },
    {
      "sourceText": "Definitive agreements are binding.",
      "targetText": "Acordurile definitive sunt obligatorii."
    },
    {
      "sourceText": "The contract is definitively signed.",
      "targetText": "Contractul este semnat definitiv."
    }
  ],
  "learningTips": [
    {
      "lang": "en",
      "text": "Remember 'definitive' means something final and settled—like a 'definition' that clearly sets the meaning."
    },
    {
      "lang": "en",
      "text": "The Romanian 'definitiv' sounds very similar to English 'definitive', making it easy to recall."
    },
    {
      "lang": "en",
      "text": "Think of 'definitive' as the last word on a topic, just like a 'final' decision that can't be changed."
    },
    {
      "lang": "en",
      "text": "Link 'definitive' to 'define'—both come from Latin roots about setting limits or boundaries."
    }
  ],
  "media": {
    "images": [],
    "audio": [
      {
        "path": "examples.0.targetText",
        "url": "/media/ms-ro/audio/definitiv-869df85a-example-1.opus",
        "lang": "ro"
      },
      {
        "path": "target.headword",
        "url": "/media/ms-ro/audio/definitiv-869df85a.opus",
        "lang": "ro"
      }
    ]
  }
}