{
  "id": "ms-en-ro-small-change",
  "parent": "ms-ro-marunt-7d12f657@79c61181d0d0a6f432f02c5f6f306bce",
  "part_of_speech": "noun",
  "tags": [
    "level:a2",
    "etymology:latin",
    "topic:people-society",
    "register:neutral",
    "property:concrete"
  ],
  "sourceLanguage": "en",
  "targetLanguage": "ro",
  "metadata": {
    "author": "mschwehl",
    "source": "swipedict-en-ro",
    "contentVersion": 1,
    "schemaVersion": "1.0"
  },
  "source": {
    "lang": "en",
    "headword": "small change",
    "definition": "Coins of low monetary value, typically used for everyday small payments.",
    "pronunciation": "/smɔːl tʃeɪndʒ/",
    "etymology": {
      "explanation": {
        "sourceText": "The English term \"small change\" combines \"small,\" meaning little in size or amount, with \"change,\" referring to coins used as money. \"Change\" originates from Old French 'changier', meaning to exchange or alter.",
        "targetText": "Cuvântul englezesc „small change” combină „small”, care înseamnă mic ca mărime sau cantitate, cu „change”, referindu-se la monede folosite ca bani. „Change” provine din franceza veche 'changier', care înseamnă a schimba sau a altera."
      },
      "source": "Etymological Dictionaries, Linguistic Analysis"
    },
    "genus": "neuter"
  },
  "target": {
    "lang": "ro",
    "headword": "mărunt",
    "genus": "neuter",
    "definition": "Bani în monede de valoare mică, folosiți frecvent pentru plăți mărunte sau zilnice.",
    "pronunciation": "/məˈrunt/",
    "etymology": {
      "explanation": {
        "sourceText": "The Romanian word „mărunt” derives from the Latin adjective 'minutus', meaning 'small' or 'tiny', and over time it evolved to denote something of small or insignificant value.",
        "targetText": "Cuvântul românesc „mărunt” provine din adjectivul latin 'minutus', care înseamnă 'mic' sau 'mărunt', și a evoluat pentru a desemna ceva de valoare mică sau nesemnificativă."
      },
      "source": "Etymological Dictionaries, Linguistic Analysis"
    }
  },
  "senses": [],
  "relatedWords": [
    {
      "sourceText": "cash",
      "targetText": "numerar"
    },
    {
      "sourceText": "money",
      "targetText": "bani"
    },
    {
      "sourceText": "cash register",
      "targetText": "casă (de marcat)"
    },
    {
      "sourceText": "coin",
      "targetText": "monedă"
    }
  ],
  "antonyms": [
    {
      "sourceText": "large sums",
      "targetText": "bani mari"
    }
  ],
  "examples": [
    {
      "sourceText": "I only have small change left in my pocket.",
      "targetText": "Am doar mărunt în buzunar."
    },
    {
      "sourceText": "Please pay with small change if possible.",
      "targetText": "Vă rog să plătiți cu mărunt, dacă este posibil."
    },
    {
      "sourceText": "The small change is in the drawer.",
      "targetText": "Măruntul este în sertar."
    },
    {
      "sourceText": "He collected his small change to buy an ice cream.",
      "targetText": "A adunat măruntul ca să cumpere o înghețată."
    }
  ],
  "learningTips": [
    {
      "lang": "en",
      "text": "Remember the Romanian word “mărunt” sounds like “marooned” – imagine being marooned with only small change in your pocket!"
    },
    {
      "lang": "en",
      "text": "Think of “mărunt” as related to “minute” (tiny) in English, helping you recall it means something small or insignificant."
    },
    {
      "lang": "en",
      "text": "When you hear “mărunt,” picture a handful of coins you use daily for small purchases – just like small change."
    },
    {
      "lang": "en",
      "text": "Associate “mărunt” with the English word “margin” to remember it relates to small amounts or minor value."
    }
  ],
  "media": {
    "images": [],
    "audio": [
      {
        "path": "examples.0.targetText",
        "url": "/media/ms-ro/audio/marunt-7d12f657-example-1.opus",
        "lang": "ro"
      },
      {
        "path": "target.headword",
        "url": "/media/ms-ro/audio/marunt-7d12f657.opus",
        "lang": "ro"
      }
    ]
  }
}