{
  "id": "ms-de-ro-ebenso",
  "parent": "ms-ro-de-asemenea-aa617170@cecd86949b3881f96549653159c94bfc",
  "part_of_speech": "adverb",
  "tags": [
    "level:b1",
    "etymology:internal",
    "topic:concepts-abstract",
    "register:neutral",
    "property:quality"
  ],
  "sourceLanguage": "de",
  "targetLanguage": "ro",
  "metadata": {
    "author": "mschwehl",
    "source": "swipedict-de-ro",
    "contentVersion": 1,
    "schemaVersion": "1.0"
  },
  "source": {
    "lang": "de",
    "headword": "ebenso",
    "definition": "in gleicher Weise, gleichfalls oder ebenso",
    "pronunciation": "/ˈeːbə̯n͡zoː/",
    "etymology": {
      "explanation": {
        "sourceText": "Das Wort „ebenso“ entstand aus der Verbindung von „eben“ (gleich, gerade) und „so“ (auf diese Weise) im Mittelhochdeutschen.",
        "targetText": "Cuvântul „ebenso“ provine din combinarea termenilor germani vechi „eben“ (egal, exact) și „so“ (așa), formând o Adverbială de mod."
      },
      "source": "Etymological Dictionaries, Linguistic Analysis"
    },
    "additional": "Es wird verwendet, um zwei Dinge oder Ideen gleichzustellen."
  },
  "target": {
    "lang": "ro",
    "headword": "de asemenea",
    "definition": "în același mod, la fel de bine sau de asemenea",
    "pronunciation": "/de aˈse̯me̯ne/",
    "etymology": {
      "explanation": {
        "sourceText": "Die Phrase „de asemenea“ stammt aus der Kombination von „de“ (von) und „asemenea“ (ähnlich), was zusammen „ebenfalls“ oder „auch“ bedeutet.",
        "targetText": "Expresia „de asemenea“ provine din combinarea prepoziției „de“ cu adjectivul „asemenea“ (asemănător), exprimând ideea de similaritate sau adăugare."
      },
      "source": "AI, Wiktionary, Linguistic Analysis"
    },
    "additional": "In der rumänischen Sprache wird es oft verwendet, um Informationen und Ideen zu verknüpfen."
  },
  "relatedWords": [
    {
      "sourceText": "auch",
      "targetText": "de asemenea"
    },
    {
      "sourceText": "gleich",
      "targetText": "la fel"
    },
    {
      "sourceText": "so",
      "targetText": "așa"
    },
    {
      "sourceText": "wie",
      "targetText": "ca"
    }
  ],
  "antonyms": [
    {
      "sourceText": "nicht ebenso",
      "targetText": "diferit"
    }
  ],
  "examples": [
    {
      "sourceText": "Ich mag Äpfel und ebenso Birnen.",
      "targetText": "Îmi plac merele și de asemenea perele."
    },
    {
      "sourceText": "Er hat das Buch gelesen, und ich ebenso.",
      "targetText": "El a citit cartea, iar eu de asemenea."
    }
  ],
  "learningTips": [
    {
      "lang": "de",
      "text": "„Ebenso“ klingt wie „eben so“ – stelle dir vor, zwei Dinge liegen eben so gleich auf der Waage."
    },
    {
      "lang": "de",
      "text": "Das rumänische „de asemenea“ kannst du dir als „de“ (von) + „asemenea“ (ähnlich) merken – also etwas, das ähnlich oder gleich ist."
    },
    {
      "lang": "de",
      "text": "Verbinde „ebenso“ mit dem deutschen „auch“ und stelle dir vor, wie du mit einem Nicken zustimmst."
    },
    {
      "lang": "de",
      "text": "Visualisiere „de asemenea“ als eine Brücke, die zwei Gedanken oder Dinge miteinander verbindet."
    }
  ],
  "media": {
    "images": [],
    "audio": [
      {
        "path": "examples.0.targetText",
        "url": "/media/ms-ro/audio/de-asemenea-aa617170-example-1.opus",
        "lang": "ro"
      },
      {
        "path": "target.headword",
        "url": "/media/ms-ro/audio/de-asemenea-aa617170.opus",
        "lang": "ro"
      }
    ]
  }
}