{
  "id": "ms-de-ro-loewe",
  "parent": "ms-ro-leu-8669f107@19d61336bc3ad0a78dbe14d1a9d96302",
  "part_of_speech": "noun",
  "tags": [
    "level:a2",
    "etymology:latin",
    "topic:animals",
    "register:neutral",
    "property:concrete"
  ],
  "sourceLanguage": "de",
  "targetLanguage": "ro",
  "metadata": {
    "author": "mschwehl",
    "source": "swipedict-de-ro",
    "contentVersion": 1,
    "schemaVersion": "1.0"
  },
  "source": {
    "lang": "de",
    "headword": "Löwe",
    "genus": "masculine",
    "definition": "Ein großes wildes Raubtier aus der Familie der Katzen, bekannt als König der Tiere.",
    "pronunciation": "/ˈløːvə/",
    "etymology": {
      "explanation": {
        "sourceText": "Das deutsche Wort „Löwe“ stammt vom althochdeutschen 'leo' ab, das aus dem Lateinischen 'leo' entlehnt wurde, welches wiederum aus dem Griechischen 'λέων' (léōn) stammt.",
        "targetText": "Cuvântul german „Löwe” provine din germana veche înaltă 'leo', împrumutat din latină 'leo', care la rândul său provine din grecescul 'λέων' (léōn)."
      },
      "source": "Etymological Dictionaries, Linguistic Analysis"
    }
  },
  "target": {
    "lang": "ro",
    "headword": "leu",
    "genus": "masculine",
    "definition": "Un animal sălbatic mare din familia felinelor, considerat regele animalelor.",
    "pronunciation": "/leu/",
    "etymology": {
      "explanation": {
        "sourceText": "Das rumänische Wort „leu“ stammt direkt vom lateinischen 'leo' ab, das aus dem Griechischen 'λέων' (léōn) entlehnt wurde.",
        "targetText": "Cuvântul românesc „leu” provine direct din latină 'leo', împrumutat din grecescul 'λέων' (léōn)."
      },
      "source": "Etymological Dictionaries, Linguistic Analysis"
    },
    "additional": "Maskulinum, Plural: lei."
  },
  "senses": [],
  "relatedWords": [
    {
      "sourceText": "Katzen",
      "targetText": "pisici"
    },
    {
      "sourceText": "König der Tiere",
      "targetText": "regele animalelor"
    },
    {
      "sourceText": "Raubtier",
      "targetText": "prădător"
    },
    {
      "sourceText": "Tiger",
      "targetText": "tigru"
    }
  ],
  "antonyms": [],
  "examples": [
    {
      "sourceText": "Der Löwe lebt in Afrika und ist sehr stark.",
      "targetText": "Leul trăiește în Africa și este foarte puternic."
    },
    {
      "sourceText": "Der Löwe brüllt laut in der Savanne.",
      "targetText": "Leul răcnește tare în savană."
    },
    {
      "sourceText": "Ein Löwe hat eine prächtige Mähne.",
      "targetText": "Un leu are o coamă impunătoare."
    },
    {
      "sourceText": "Der König der Tiere ist der Löwe.",
      "targetText": "Regele animalelor este leul."
    }
  ],
  "learningTips": [
    {
      "lang": "de",
      "text": "Das rumänische 'leu' klingt fast wie das deutsche Wort 'Leo', ein häufiger Name für Löwen in Geschichten."
    },
    {
      "lang": "de",
      "text": "Das Wort 'leu' kommt direkt aus dem Lateinischen 'leo' – das hilft dir, die Verbindung zu merken."
    },
    {
      "lang": "de",
      "text": "Erinnere dich an den Löwen als 'König der Tiere' und den rumänischen 'leu' als starken König im Tierreich."
    },
    {
      "lang": "de",
      "text": "Stell dir vor, ein Löwe namens 'Leu' brüllt laut in der Savanne – so merkst du dir das Wort."
    }
  ],
  "media": {
    "images": [],
    "audio": [
      {
        "path": "examples.0.targetText",
        "url": "/media/ms-ro/audio/leu-8669f107-example-1.opus",
        "lang": "ro"
      },
      {
        "path": "target.headword",
        "url": "/media/ms-ro/audio/leu-8669f107.opus",
        "lang": "ro"
      }
    ]
  }
}