{
  "id": "ms-en-ro-jealousy",
  "parent": "ms-ro-gelozie-6442e65a@df426c39bf42ec032aaa2fed658adc20",
  "part_of_speech": "noun",
  "tags": [
    "level:b2",
    "etymology:italian",
    "topic:emotions-character",
    "register:neutral",
    "property:abstract"
  ],
  "sourceLanguage": "en",
  "targetLanguage": "ro",
  "metadata": {
    "author": "mschwehl",
    "source": "swipedict-en-ro",
    "contentVersion": 1,
    "schemaVersion": "1.0"
  },
  "source": {
    "lang": "en",
    "headword": "jealousy",
    "genus": "feminine",
    "definition": "The feeling of fear or anxiety about losing something valuable, especially the love or affection of a partner.",
    "pronunciation": "/ˈdʒɛl.əs.i/",
    "etymology": {
      "explanation": {
        "sourceText": "The English word \"jealousy\" originates from the Old French 'jalousie', which itself comes from the Italian 'gelosia', derived from Latin 'zelus' meaning zeal or ardent rivalry.",
        "targetText": "Cuvântul englezesc „jealousy” provine din franceza veche 'jalousie', care la rândul său vine din italianul 'gelosia', derivat din latinul 'zelus' însemnând zel sau rivalitate aprinsă."
      },
      "source": "Etymological Dictionaries, Linguistic Analysis"
    },
    "additional": "null"
  },
  "target": {
    "lang": "ro",
    "headword": "gelozie",
    "genus": "feminine",
    "definition": "Sentimentul de teamă sau neliniște că poți pierde ceva valoros, de obicei dragostea partenerului.",
    "pronunciation": "/ɡeˈlozje/",
    "etymology": {
      "explanation": {
        "sourceText": "The Romanian word \"gelozie\" was borrowed from the Italian \"gelosia\", which in turn comes from the Latin \"zelus\" (zeal, jealousy).",
        "targetText": "Cuvântul românesc „gelozie” a fost împrumutat din italianul „gelosia”, care provine la rândul său din latinul „zelus” (entuziasm, gelozie)."
      },
      "source": "Etymological Dictionaries, Linguistic Analysis"
    }
  },
  "senses": [],
  "relatedWords": [
    {
      "sourceText": "Jealous",
      "targetText": "gelos"
    },
    {
      "sourceText": "Love",
      "targetText": "dragoste"
    },
    {
      "sourceText": "Distrust",
      "targetText": "neîncredere"
    },
    {
      "sourceText": "Envy",
      "targetText": "invidie"
    }
  ],
  "antonyms": [
    {
      "sourceText": "Trust",
      "targetText": "încredere"
    }
  ],
  "examples": [
    {
      "sourceText": "His jealousy destroyed the relationship.",
      "targetText": "Gelozia lui a distrus relația."
    },
    {
      "sourceText": "Jealousy can lead to problems.",
      "targetText": "Gelozia poate duce la probleme."
    },
    {
      "sourceText": "She showed great jealousy when he talked to others.",
      "targetText": "Ea a arătat multă gelozie când el vorbea cu alții."
    },
    {
      "sourceText": "Jealousy is a strong emotion.",
      "targetText": "Gelozia este o emoție puternică."
    }
  ],
  "learningTips": [
    {
      "lang": "en",
      "text": "Remember 'jealousy' sounds like 'jelly'—imagine your feelings wobbling when you fear losing someone’s love."
    },
    {
      "lang": "en",
      "text": "The Romanian word 'gelozie' is similar to the Italian 'gelosia', so linking them helps recall the meaning of jealousy."
    },
    {
      "lang": "en",
      "text": "Think of 'jealousy' as a 'yellow' emotion—yellow often symbolizes caution or warning, just like jealousy warns of potential loss."
    },
    {
      "lang": "en",
      "text": "The root 'zelus' means zeal or passion, so jealousy is an intense feeling related to strong emotions and desire."
    }
  ],
  "media": {
    "images": [],
    "audio": [
      {
        "path": "examples.0.targetText",
        "url": "/media/ms-ro/audio/gelozie-6442e65a-example-1.opus",
        "lang": "ro"
      },
      {
        "path": "target.headword",
        "url": "/media/ms-ro/audio/gelozie-6442e65a.opus",
        "lang": "ro"
      }
    ]
  }
}