{
  "id": "ms-en-ro-journey",
  "parent": "ms-ro-calatorie-766fa24e@24f2eabce8a1fa8649f387fd0a25fa53",
  "part_of_speech": "noun",
  "tags": [
    "level:a1",
    "etymology:latin",
    "topic:leisure-culture",
    "topic:transport-movement",
    "register:neutral",
    "property:concrete"
  ],
  "sourceLanguage": "en",
  "targetLanguage": "ro",
  "metadata": {
    "author": "mschwehl",
    "source": "swipedict-en-ro",
    "contentVersion": 1,
    "schemaVersion": "1.0"
  },
  "source": {
    "lang": "en",
    "headword": "journey",
    "genus": "feminine",
    "definition": "A planned or undertaken trip from one place to another, often for leisure, visiting, or work purposes.",
    "pronunciation": "/ˈdʒɜːrni/",
    "etymology": {
      "explanation": {
        "sourceText": "The English word 'journey' comes from the Old French 'jornee', meaning a day's travel or work, which itself derives from the Latin 'diurnum', meaning 'day'. It originally referred to the distance or travel accomplished in a single day.",
        "targetText": "Cuvântul englezesc „journey” provine din franceza veche 'jornee', care însemna o călătorie sau muncă de o zi, derivat din latină 'diurnum', însemnând „zi”. Inițial se referea la distanța sau călătoria realizată într-o singură zi."
      },
      "source": "Etymological Dictionaries, Linguistic Analysis"
    }
  },
  "target": {
    "lang": "ro",
    "headword": "călătorie",
    "genus": "feminine",
    "definition": "Deplasarea planificată sau efectuată de la un loc la altul, de obicei pentru recreere, vizită sau muncă.",
    "pronunciation": "/kə.ləˈto.ri.e/",
    "etymology": {
      "explanation": {
        "sourceText": "The Romanian word 'călătorie' comes from the Latin 'calator', meaning 'traveler', derived from 'calare' (to call, to summon), and evolved into a term for a trip or travel.",
        "targetText": "Cuvântul românesc „călătorie” derivă din latină, de la 'calator' (călător), care provine din verbul 'calare' (a chema, a striga), evoluând spre sensul de deplasare sau călătorie."
      },
      "source": "Etymological Dictionaries, Linguistic Analysis"
    }
  },
  "senses": [],
  "relatedWords": [
    {
      "sourceText": "ride",
      "targetText": "călătorie"
    },
    {
      "sourceText": "to travel",
      "targetText": "a călători"
    },
    {
      "sourceText": "traveler",
      "targetText": "călător"
    },
    {
      "sourceText": "tour",
      "targetText": "tur"
    }
  ],
  "antonyms": [
    {
      "sourceText": "home",
      "targetText": "acasă"
    }
  ],
  "examples": [
    {
      "sourceText": "The journey to Romania took ten hours.",
      "targetText": "Călătoria în România a durat zece ore."
    },
    {
      "sourceText": "We are planning a journey to the sea in summer.",
      "targetText": "Planificăm o călătorie la mare vara."
    },
    {
      "sourceText": "After the long journey, she was very tired.",
      "targetText": "După călătoria lungă, ea era foarte obosită."
    },
    {
      "sourceText": "The journey was full of exciting experiences.",
      "targetText": "Călătoria a fost plină de experiențe interesante."
    }
  ],
  "learningTips": [
    {
      "lang": "en",
      "text": "Remember 'călătorie' by thinking of a 'call to tour'—a call to travel, which links to the Latin root 'calare' meaning 'to call'."
    },
    {
      "lang": "en",
      "text": "The ending '-ie' is common in Romanian nouns that describe actions or concepts, similar to English '-y' or '-ie' endings like 'journey'."
    },
    {
      "lang": "en",
      "text": "Think of 'călător' as the traveler and 'călătorie' as the journey they take—this helps connect the words in your mind."
    },
    {
      "lang": "en",
      "text": "Imagine you’re inviting someone on a journey by 'calling' them—this helps you remember the root 'calare' and the meaning of 'călătorie'."
    }
  ],
  "media": {
    "images": [],
    "audio": [
      {
        "path": "examples.0.targetText",
        "url": "/media/ms-ro/audio/calatorie-766fa24e-example-1.opus",
        "lang": "ro"
      },
      {
        "path": "target.headword",
        "url": "/media/ms-ro/audio/calatorie-766fa24e.opus",
        "lang": "ro"
      }
    ]
  }
}