{
  "id": "ms-en-ro-meteor",
  "parent": "ms-ro-meteor-a2551c62@623363eae254a4a3d1cf32da350ed4ab",
  "part_of_speech": "noun",
  "tags": [
    "level:b1",
    "etymology:greek",
    "topic:nature-environment",
    "register:neutral",
    "property:concrete"
  ],
  "sourceLanguage": "en",
  "targetLanguage": "ro",
  "metadata": {
    "author": "mschwehl",
    "source": "swipedict-en-ro",
    "contentVersion": 1,
    "schemaVersion": "1.0"
  },
  "source": {
    "lang": "en",
    "headword": "meteor",
    "genus": "masculine",
    "definition": "A bright streak of light in the sky caused by a solid object burning up as it enters Earth's atmosphere.",
    "pronunciation": "/ˈmiːtiər/",
    "etymology": {
      "explanation": {
        "sourceText": "The English word 'meteor' comes from the Greek 'meteōros', meaning 'high in the air', and entered English through Latin.",
        "targetText": "Cuvântul englezesc „meteor“ provine din grecescul ‚meteōros‘, care înseamnă ‚înalt în aer‘, fiind preluat în engleză prin latină."
      },
      "source": "Etymological Dictionaries, Linguistic Analysis"
    }
  },
  "target": {
    "lang": "ro",
    "headword": "meteor",
    "genus": "masculine",
    "definition": "Un corp solid care strălucește în atmosferă când arde la intrarea în atmosferă, vizibil ca o dungă luminoasă pe cer.",
    "pronunciation": "/meˈte.or/",
    "etymology": {
      "explanation": {
        "sourceText": "The Romanian word 'meteor' comes directly from the Greek 'meteōros', meaning 'high in the air', and was adopted into Romanian through Latin.",
        "targetText": "Cuvântul românesc „meteor“ provine direct din grecescul ‚meteōros‘, care înseamnă ‚înalt în aer‘, preluat prin latină în limba română."
      },
      "source": "Etymological Dictionaries, Linguistic Analysis"
    }
  },
  "senses": [],
  "relatedWords": [
    {
      "sourceText": "asteroid",
      "targetText": "asteroid"
    },
    {
      "sourceText": "atmosphere",
      "targetText": "atmosferă"
    },
    {
      "sourceText": "comet",
      "targetText": "cometă"
    },
    {
      "sourceText": "meteorite",
      "targetText": "meteorit"
    }
  ],
  "antonyms": [],
  "examples": [
    {
      "sourceText": "At night, many meteors could be seen in the sky.",
      "targetText": "Noaptea s-au putut vedea mulți meteori pe cer."
    },
    {
      "sourceText": "A meteor burned up in Earth's atmosphere.",
      "targetText": "Un meteor a ars în atmosfera Pământului."
    },
    {
      "sourceText": "Meteors form when small rock fragments enter the atmosphere.",
      "targetText": "Meteori se formează când mici bucăți de piatră intră în atmosferă."
    },
    {
      "sourceText": "The meteor left a glowing trail in the sky.",
      "targetText": "Meteorul a lăsat o urmă luminoasă pe cer."
    }
  ],
  "learningTips": [
    {
      "lang": "en",
      "text": "Remember 'meteor' as a 'meter' of light streaking across the sky—both words start similarly and relate to length and brightness."
    },
    {
      "lang": "en",
      "text": "Think of a meteor as a 'meteor shower'—a spectacular natural light show visible from Earth."
    },
    {
      "lang": "en",
      "text": "The word 'meteor' comes from Greek meaning 'high in the air'—imagine something glowing high above you."
    },
    {
      "lang": "en",
      "text": "Link 'meteor' with 'meteorite'—the first burns in the atmosphere, the second lands on Earth; both share the same root."
    }
  ],
  "media": {
    "images": [],
    "audio": [
      {
        "path": "examples.0.targetText",
        "url": "/media/ms-ro/audio/meteor-a2551c62-example-1.opus",
        "lang": "ro"
      },
      {
        "path": "target.headword",
        "url": "/media/ms-ro/audio/meteor-a2551c62.opus",
        "lang": "ro"
      }
    ]
  }
}